LICENSE
README.md
setup.py
start.py
octobot_market_making/__init__.py
octobot_market_making/cli.py
octobot_market_making/constants.py
octobot_market_making.egg-info/PKG-INFO
octobot_market_making.egg-info/SOURCES.txt
octobot_market_making.egg-info/dependency_links.txt
octobot_market_making.egg-info/entry_points.txt
octobot_market_making.egg-info/not-zip-safe
octobot_market_making.egg-info/requires.txt
octobot_market_making.egg-info/top_level.txt
octobot_market_making/config/default_config.json