Metadata-Version: 2.4
Name: octobot_market_making
Version: 2.0.16
Summary: Cryptocurrencies market making bot
Home-page: https://github.com/Drakkar-Software/OctoBot-Market-Making
Author: Drakkar-Software
Author-email: contact@drakkar.software
License: GPL-3.0
Classifier: Development Status :: 4 - Beta
Classifier: Operating System :: OS Independent
Classifier: Operating System :: MacOS :: MacOS X
Classifier: Operating System :: Microsoft :: Windows
Classifier: Operating System :: POSIX
Classifier: Programming Language :: Python :: 3.10
Requires-Python: >=3.10
License-File: LICENSE
Requires-Dist: OctoBot[full]==2.0.16
Dynamic: author
Dynamic: author-email
Dynamic: classifier
Dynamic: description
Dynamic: description-content-type
Dynamic: home-page
Dynamic: license
Dynamic: license-file
Dynamic: requires-dist
Dynamic: requires-python
Dynamic: summary
